setup.py
gokul_fraud/__init__.py
gokul_fraud/operations.py
gokul_fraud.egg-info/PKG-INFO
gokul_fraud.egg-info/SOURCES.txt
gokul_fraud.egg-info/dependency_links.txt
gokul_fraud.egg-info/top_level.txt