Metadata-Version: 2.4
Name: gokul_fraud
Version: 0.1.4
Summary: A simple Python package for math gokul_fraud and geometry calculations
Classifier: Programming Language :: Python :: 3
Classifier: License :: OSI Approved :: MIT License
Classifier: Operating System :: OS Independent
Requires-Python: >=3.6
Dynamic: classifier
Dynamic: requires-python
Dynamic: summary
